ndev/__init__.py
ndev/app.py
ndev/hx_urllib.py
ndev/py.typed
ndev/shutil_ext.py
ndev/types.py
ndev/commands/__init__.py
ndev/commands/git_sync.py
ndev/commands/release.py
ndev/impl/__init__.py
ndev/impl/listener.py
ndev/protocols/__init__.py
ndev/protocols/listener.py
ndev/protocols/verbosity.py
ndev/services/__init__.py
ndev/services/git/__init__.py
ndev/services/git/syncer.py
ndev/services/git/syncer_conf.py
ndev/services/git/tool.py
ndev/services/releaser/__init__.py
ndev/services/releaser/requirements.py
ndev-0.9.0.dist-info/METADATA
ndev-0.9.0.dist-info/WHEEL
ndev-0.9.0.dist-info/entry_points.txt
ndev-0.9.0.dist-info/licenses/LICENSE
ndev-0.9.0.dist-info/RECORD
