Metadata-Version: 2.4
Name: ndev
Version: 0.9.0
Summary: Python projects management toolset
License-File: LICENSE
Requires-Python: <3.14,>=3.11
Requires-Dist: cleo
Requires-Dist: gitpython>=3.1.44
Requires-Dist: pydantic>=2.9.2
Requires-Dist: pygit2>=1.19
Requires-Dist: tomli<3.0.0,>=2.0.1; python_version < '3.11'
